{
    "transactions": [
        {
            "recipientId": "QVSrmQCd7h9Y6C8dXPVBsS4NVoF7aeWEbb",
            "amount": 497763910864
        },
        {
            "recipientId": "QfyJKz1ZxbkPRrGv6c1H99nFJMeXiSZqbp",
            "amount": 144587494472
        },
        {
            "recipientId": "QdTtHQsEubw2aJtaxv8vkV4NiYv24P8AwW",
            "amount": 129590716799
        },
        {
            "recipientId": "QTk1JMqW1fVwCB9pVp53koMwMtD6fGtgbB",
            "amount": 114113947964
        },
        {
            "recipientId": "QY768oLfuX9uWs6aYcY5JYg2aoZom1qTND",
            "amount": 108838196346
        },
        {
            "recipientId": "QY4duDqWcTxMTbb9yCWYkQC3zu2qVSpfS2",
            "amount": 68223971419
        },
        {
            "recipientId": "QgYGJh4U2gQqt5zy2BHhaifHmazgqJYjja",
            "amount": 63113194057
        },
        {
            "recipientId": "QRsFu5TXAWZ65EvSxnexRK2cYTNSLGsyvy",
            "amount": 58237507894
        },
        {
            "recipientId": "QbAUPhKp7f556kBCJSzBA2hwayi9kNBh5p",
            "amount": 50879178357
        },
        {
            "recipientId": "QYDefXMWZoZBEZxX5ipk79BcESwxzV7eNb",
            "amount": 41996612720
        },
        {
            "recipientId": "QSyBEx2CMToXke2WFeWAuxsqN2CXrWF99P",
            "amount": 19678900556
        },
        {
            "recipientId": "QdepdJT1t1KtiAvNidoizFMdAYP79uWseT",
            "amount": 19675047356
        }
    ],
    "transactionsPending": [],
    "donations": [],
    "donationsPercentage": []
}