{
    "transactions": [
        {
            "recipientId": "QVSrmQCd7h9Y6C8dXPVBsS4NVoF7aeWEbb",
            "amount": 468414003836
        },
        {
            "recipientId": "QfyJKz1ZxbkPRrGv6c1H99nFJMeXiSZqbp",
            "amount": 136062108385
        },
        {
            "recipientId": "QdTtHQsEubw2aJtaxv8vkV4NiYv24P8AwW",
            "amount": 121949593353
        },
        {
            "recipientId": "QTGUbwJdeCB56dA1yZN7cNrk4WV6USCMMb",
            "amount": 109485445461
        },
        {
            "recipientId": "QTk1JMqW1fVwCB9pVp53koMwMtD6fGtgbB",
            "amount": 107385389123
        },
        {
            "recipientId": "QY768oLfuX9uWs6aYcY5JYg2aoZom1qTND",
            "amount": 102420714335
        },
        {
            "recipientId": "QY4duDqWcTxMTbb9yCWYkQC3zu2qVSpfS2",
            "amount": 64201246640
        },
        {
            "recipientId": "QgYGJh4U2gQqt5zy2BHhaifHmazgqJYjja",
            "amount": 59391818647
        },
        {
            "recipientId": "QRsFu5TXAWZ65EvSxnexRK2cYTNSLGsyvy",
            "amount": 54803620051
        },
        {
            "recipientId": "QYDefXMWZoZBEZxX5ipk79BcESwxzV7eNb",
            "amount": 39520345052
        },
        {
            "recipientId": "QdNFhrZMJCza6w21DzJJTwP36urQAq4hTe",
            "amount": 23919140215
        },
        {
            "recipientId": "QSyBEx2CMToXke2WFeWAuxsqN2CXrWF99P",
            "amount": 18518563518
        },
        {
            "recipientId": "QdepdJT1t1KtiAvNidoizFMdAYP79uWseT",
            "amount": 18514937517
        },
        {
            "recipientId": "QcwDC8d4PgHTUunBcdvVXBQRnxyzpHoTor",
            "amount": 16659266813
        },
        {
            "recipientId": "QjrAqXZLVff1UVH1VP917mDeoSCMgAYYn4",
            "amount": 15952559070
        }
    ],
    "transactionsPending": [],
    "donations": [],
    "donationsPercentage": []
}